deltastream/__init__.py
deltastream/api/__init__.py
deltastream/api/blob.py
deltastream/api/conn.py
deltastream/api/dpconn.py
deltastream/api/error.py
deltastream/api/handlers.py
deltastream/api/models.py
deltastream/api/resultset_rows.py
deltastream/api/rows.py
deltastream/api/streaming_rows.py
deltastream/api/controlplane/__init__.py
deltastream/api/controlplane/api-server-v2.yaml
deltastream/api/controlplane/openapi_client/__init__.py
deltastream/api/controlplane/openapi_client/api_client.py
deltastream/api/controlplane/openapi_client/api_response.py
deltastream/api/controlplane/openapi_client/configuration.py
deltastream/api/controlplane/openapi_client/exceptions.py
deltastream/api/controlplane/openapi_client/py.typed
deltastream/api/controlplane/openapi_client/rest.py
deltastream/api/controlplane/openapi_client/api/__init__.py
deltastream/api/controlplane/openapi_client/api/deltastream_api.py
deltastream/api/controlplane/openapi_client/models/__init__.py
deltastream/api/controlplane/openapi_client/models/dataplane_request.py
deltastream/api/controlplane/openapi_client/models/error_response.py
deltastream/api/controlplane/openapi_client/models/organization.py
deltastream/api/controlplane/openapi_client/models/result_set.py
deltastream/api/controlplane/openapi_client/models/result_set_columns_inner.py
deltastream/api/controlplane/openapi_client/models/result_set_context.py
deltastream/api/controlplane/openapi_client/models/result_set_data_inner_inner.py
deltastream/api/controlplane/openapi_client/models/result_set_metadata.py
deltastream/api/controlplane/openapi_client/models/result_set_partition_info.py
deltastream/api/controlplane/openapi_client/models/statement_request.py
deltastream/api/controlplane/openapi_client/models/statement_request_parameters.py
deltastream/api/controlplane/openapi_client/models/statement_status.py
deltastream/api/controlplane/openapi_client/models/version.py
deltastream/api/controlplane/openapi_client/test/__init__.py
deltastream_connector-0.3.0.dist-info/METADATA
deltastream_connector-0.3.0.dist-info/WHEEL
deltastream_connector-0.3.0.dist-info/entry_points.txt
deltastream_connector-0.3.0.dist-info/licenses/LICENSE
deltastream_connector-0.3.0.dist-info/RECORD
