Metadata-Version: 2.4
Name: deltastream-connector
Version: 0.3.0
Summary: An OpenAPI client for the DeltaStream API
Project-URL: Homepage, https://github.com/deltastreaminc/deltastream-connector-python
Project-URL: Issues, https://github.com/deltastreaminc/deltastream-connector-python/issues
Author-email: "DeltaStream Inc." <support@deltastream.com>
License-Expression: Apache-2.0
License-File: LICENSE
Classifier: Operating System :: OS Independent
Classifier: Programming Language :: Python :: 3
Requires-Python: >=3.11
Requires-Dist: lazy-imports>=1.0.0
Requires-Dist: pydantic>=2
Requires-Dist: python-dateutil>=2.8.2
Requires-Dist: typing-extensions>=4.7.1
Requires-Dist: urllib3<3.0.0,>=1.25.3
Requires-Dist: websockets>=14.2
